CHANGES.txt
CONTRIBUTORS.txt
README.txt
bootstrap.py
buildout.cfg
setup.py
src/collective/__init__.py
src/collective.recipe.funkload.egg-info/PKG-INFO
src/collective.recipe.funkload.egg-info/SOURCES.txt
src/collective.recipe.funkload.egg-info/dependency_links.txt
src/collective.recipe.funkload.egg-info/entry_points.txt
src/collective.recipe.funkload.egg-info/namespace_packages.txt
src/collective.recipe.funkload.egg-info/not-zip-safe
src/collective.recipe.funkload.egg-info/requires.txt
src/collective.recipe.funkload.egg-info/top_level.txt
src/collective/recipe/__init__.py
src/collective/recipe/funkload/README.txt
src/collective/recipe/funkload/__init__.py
src/collective/recipe/funkload/dispatcher.py
src/collective/recipe/funkload/tests/Plone.conf
src/collective/recipe/funkload/tests/Simple.conf
src/collective/recipe/funkload/tests/__init__.py
src/collective/recipe/funkload/tests/test_Plone.py
src/collective/recipe/funkload/tests/test_Simple.py
src/collective/recipe/funkload/tests/test_docs.py