Metadata-Version: 1.0
Name: collective.recipe.funkload
Version: 0.3.1
Summary: Makes installing funkload, running tests and generating reports a 'no-brainer'
Home-page: http://pypi.python.org/pypi/collective.recipe.funkload
Author: Alan Hoey
Author-email: alan.hoey@teamrubber.com
License: ZPL
Keywords: funkload recipe
Platform: UNKNOWN
Classifier: Framework :: Buildout
Classifier: Intended Audience :: Developers
Classifier: Topic :: Software Development :: Build Tools
Classifier: Topic :: Software Development :: Libraries :: Python Modules
Classifier: License :: OSI Approved :: Zope Public License
